GenshinImpactTools/__init__.py
GenshinImpactTools/error.py
GenshinImpactTools/gui.py
GenshinImpactTools/main.py
GenshinImpactTools/run_api.py
GenshinImpactTools/shell.py
GenshinImpactTools-1.0.dist-info/LICENSE
GenshinImpactTools-1.0.dist-info/METADATA
GenshinImpactTools-1.0.dist-info/WHEEL
GenshinImpactTools-1.0.dist-info/top_level.txt
GenshinImpactTools-1.0.dist-info/RECORD
