Metadata-Version: 2.1
Name: GenshinImpactTools
Version: 1.0
Summary: Genshin Impact Tools
Home-page: UNKNOWN
Author: MingxuanGame
Author-email: mingxuangame@outlook.com
License: MIT License
Platform: UNKNOWN
